discrete/__init__.py
discrete/checks.py
discrete/messages.py
discrete/plot.py
library/__init__.py
library/systems.py
plotcdf-0.0.1.dist-info/LICENSE.txt
plotcdf-0.0.1.dist-info/METADATA
plotcdf-0.0.1.dist-info/WHEEL
plotcdf-0.0.1.dist-info/top_level.txt
plotcdf-0.0.1.dist-info/RECORD
