Metadata-Version: 2.1
Name: plotcdf
Version: 0.0.1
Summary: This python package allows us to plot beautiful cumulative distributions functions for discrete random variables.
Home-page: https://github.com/parcr/plotcdf
Author: PedroCR
Author-email: pedro.cortereal@magentakoncept.com
License: UNKNOWN
Platform: UNKNOWN
Classifier: Programming Language :: Python :: 3
Classifier: License :: OSI Approved :: MIT License
Classifier: Operating System :: OS Independent
Requires-Python: >=3.6
Requires-Dist: matplotlib (>=3.1)
Requires-Dist: numpy (>=1.16)
